shotgrid_mcp_server/__init__.py
shotgrid_mcp_server/__main__.py
shotgrid_mcp_server/api_client.py
shotgrid_mcp_server/api_models.py
shotgrid_mcp_server/asgi.py
shotgrid_mcp_server/cli.py
shotgrid_mcp_server/connection_pool.py
shotgrid_mcp_server/constants.py
shotgrid_mcp_server/custom_types.py
shotgrid_mcp_server/data_types.py
shotgrid_mcp_server/error_handler.py
shotgrid_mcp_server/exceptions.py
shotgrid_mcp_server/filters.py
shotgrid_mcp_server/http_context.py
shotgrid_mcp_server/logger.py
shotgrid_mcp_server/mockgun_ext.py
shotgrid_mcp_server/models.py
shotgrid_mcp_server/py.typed
shotgrid_mcp_server/response_models.py
shotgrid_mcp_server/schema_cache.py
shotgrid_mcp_server/schema_loader.py
shotgrid_mcp_server/schema_resources.py
shotgrid_mcp_server/schema_validator.py
shotgrid_mcp_server/server.py
shotgrid_mcp_server/shotgun_args.py
shotgrid_mcp_server/utils.py
shotgrid_mcp_server/data/__init__.py
shotgrid_mcp_server/data/entity_schema.bin
shotgrid_mcp_server/data/schema.bin
shotgrid_mcp_server/tools/__init__.py
shotgrid_mcp_server/tools/api_tools.py
shotgrid_mcp_server/tools/base.py
shotgrid_mcp_server/tools/create_tools.py
shotgrid_mcp_server/tools/delete_tools.py
shotgrid_mcp_server/tools/helper_types.py
shotgrid_mcp_server/tools/note_tools.py
shotgrid_mcp_server/tools/playlist_tools.py
shotgrid_mcp_server/tools/read_tools.py
shotgrid_mcp_server/tools/search_tools.py
shotgrid_mcp_server/tools/thumbnail_tools.py
shotgrid_mcp_server/tools/types.py
shotgrid_mcp_server/tools/update_tools.py
shotgrid_mcp_server/tools/utils_date.py
shotgrid_mcp_server/tools/utils_file.py
shotgrid_mcp_server/tools/vendor_tools.py
shotgrid_mcp_server-0.14.1.dist-info/METADATA
shotgrid_mcp_server-0.14.1.dist-info/WHEEL
shotgrid_mcp_server-0.14.1.dist-info/entry_points.txt
shotgrid_mcp_server-0.14.1.dist-info/licenses/LICENSE
shotgrid_mcp_server-0.14.1.dist-info/RECORD
