Metadata-Version: 2.4
Name: shotgrid-mcp-server
Version: 0.14.1
Summary: A Model Context Protocol (MCP) server implementation using fastmcp
Project-URL: Homepage, https://github.com/loonghao/shotgrid-mcp-server
Project-URL: Repository, https://github.com/loonghao/shotgrid-mcp-server.git
Project-URL: Issues, https://github.com/loonghao/shotgrid-mcp-server/issues
Project-URL: Changelog, https://github.com/loonghao/shotgrid-mcp-server/blob/main/CHANGELOG.md
Author-email: Hal Long <hal.long@outlook.com>
License: MIT
License-File: LICENSE
Keywords: Flow Production Tracking,api,mcp,server,shotgrid
Classifier: Development Status :: 4 - Beta
Classifier: Intended Audience :: Developers
Classifier: License :: OSI Approved :: MIT License
Classifier: Operating System :: OS Independent
Classifier: Programming Language :: Python :: 3
Classifier: Programming Language :: Python :: 3.10
Classifier: Programming Language :: Python :: 3.11
Classifier: Programming Language :: Python :: 3.12
Classifier: Topic :: Software Development :: Libraries :: Python Modules
Requires-Python: <3.13,>=3.10
Requires-Dist: aiohttp>=3.12.14
Requires-Dist: click>=8.0.0
Requires-Dist: diskcache-rs>=0.4.4
Requires-Dist: fastmcp>=2.13.0
Requires-Dist: mcp>=1.10.0
Requires-Dist: pendulum<4.0.0,>=3.1.0
Requires-Dist: platformdirs>=4.1.0
Requires-Dist: pydantic[email]>=2.0.0
Requires-Dist: python-dotenv>=1.0.0
Requires-Dist: python-slugify<9.0.0,>=8.0.4
Requires-Dist: requests>=2.32.4
Requires-Dist: shotgrid-query>=0.1.0
Requires-Dist: shotgun-api3>=3.8.2
Requires-Dist: tenacity<10.0.0,>=9.1.2
Requires-Dist: uvicorn[standard]>=0.35.0
Requires-Dist: websockets>=15.0.1
Provides-Extra: dev
Requires-Dist: black>=23.12.1; extra == 'dev'
Requires-Dist: coverage>=7.4.0; extra == 'dev'
Requires-Dist: flake8>=7.0.0; extra == 'dev'
Requires-Dist: isort>=5.13.2; extra == 'dev'
Requires-Dist: mypy>=1.8.0; extra == 'dev'
Requires-Dist: nox>=2023.4.22; extra == 'dev'
Requires-Dist: pytest-cov>=4.1.0; extra == 'dev'
Requires-Dist: pytest>=7.4.4; extra == 'dev'
Requires-Dist: ruff>=0.1.11; extra == 'dev'
Requires-Dist: uv>=0.9.6; extra == 'dev'
Provides-Extra: lint
Requires-Dist: black; extra == 'lint'
Requires-Dist: mypy; extra == 'lint'
Requires-Dist: ruff; extra == 'lint'
Requires-Dist: types-requests; extra == 'lint'
Provides-Extra: test
Requires-Dist: pytest-asyncio>=0.21.0; extra == 'test'
Requires-Dist: pytest-cov>=4.0.0; extra == 'test'
Requires-Dist: pytest-mock>=3.10.0; extra == 'test'
Requires-Dist: pytest>=7.0.0; extra == 'test'
Requires-Dist: pyyaml; extra == 'test'
